llm_wrapper_mcp_server/__init__.py
llm_wrapper_mcp_server/__main__.py
llm_wrapper_mcp_server/llm_client.py
llm_wrapper_mcp_server/llm_mcp_server.py
llm_wrapper_mcp_server/llm_mcp_wrapper.py
llm_wrapper_mcp_server/logger.py
llm_wrapper_mcp_server-0.1.3.dist-info/METADATA
llm_wrapper_mcp_server-0.1.3.dist-info/WHEEL
llm_wrapper_mcp_server-0.1.3.dist-info/entry_points.txt
llm_wrapper_mcp_server-0.1.3.dist-info/licenses/LICENSE
llm_wrapper_mcp_server-0.1.3.dist-info/RECORD
