Metadata-Version: 2.4
Name: llm-wrapper-mcp-server
Version: 0.1.3
Summary: Wrap a call to any remote LLM model and expose it as an MCP server tool to allow your main model to communicate with other models.
Author-email: Mateusz <matdev83@github.com>
License: MIT
License-File: LICENSE
Requires-Python: >=3.8
Requires-Dist: fastapi>=0.104.0
Requires-Dist: llm-accounting>=0.1.0
Requires-Dist: pydantic-settings>=2.0.0
Requires-Dist: pydantic>=2.4.2
Requires-Dist: python-dotenv>=1.0.0
Requires-Dist: requests>=2.31.0
Requires-Dist: tiktoken>=0.6.0
Requires-Dist: uvicorn>=0.24.0
Provides-Extra: dev
Requires-Dist: black>=23.9.1; extra == 'dev'
Requires-Dist: isort>=5.12.0; extra == 'dev'
Requires-Dist: mypy>=1.5.1; extra == 'dev'
Requires-Dist: pytest-mock>=3.12.0; extra == 'dev'
Requires-Dist: pytest>=7.4.0; extra == 'dev'
